MANIFEST.in
README.md
setup.cfg
setup.py
django_session_notifier.egg-info/PKG-INFO
django_session_notifier.egg-info/SOURCES.txt
django_session_notifier.egg-info/dependency_links.txt
django_session_notifier.egg-info/not-zip-safe
django_session_notifier.egg-info/top_level.txt
djangosessionnotifier/__init__.py
djangosessionnotifier/helper.py
djangosessionnotifier/middleware.py
djangosessionnotifier/templates/djangosessionnotifier/notifier.html