Metadata-Version: 1.0
Name: django-session-notifier
Version: 0.0.2
Summary: Displays notification box in all views if user is session authenticated
Home-page: https://github.com/willandskill/django-session-notifier
Author: Will & Skill
Author-email: info@willandskill.se
License: MIT licence, see LICENCE.txt
Platform: UNKNOWN
